eslogging/__init__.py
eslogging/handlers.py
eslogging/serializers.py
eslogging-1.0.8.dist-info/LICENSE
eslogging-1.0.8.dist-info/METADATA
eslogging-1.0.8.dist-info/WHEEL
eslogging-1.0.8.dist-info/top_level.txt
eslogging-1.0.8.dist-info/RECORD
