Metadata-Version: 2.1
Name: eslogging
Version: 1.0.8
Summary: Elasticsearch Log handler for the logging library
Home-page: https://github.com/asuiu/eslogging
Author: Andrei Suiu
Author-email: andrei.suiu@gmail.com
License: Apache2
Keywords: logging elasticsearch handler log instrumentation
Platform: UNKNOWN
Classifier: Development Status :: 5 - Production/Stable
Classifier: Intended Audience :: Developers
Classifier: Topic :: System :: Logging
Classifier: Topic :: Software Development :: Libraries
Classifier: Topic :: Internet :: Log Analysis
Classifier: License :: OSI Approved :: Apache Software License
Classifier: Programming Language :: Python :: 3.7
Classifier: Programming Language :: Python :: 3.8
Classifier: Programming Language :: Python :: Implementation :: CPython
Classifier: Programming Language :: Python :: Implementation :: PyPy
License-File: LICENSE
Requires-Dist: elasticsearch (>=5.4.0) ; python_version >= "3"
Requires-Dist: requests (>=2.24.0) ; python_version >= "3"
Requires-Dist: pydantic (>=1.6.1) ; python_version >= "3"
